{
  "dist/umd/popper.js": {
    "bundled": 42864,
    "minified": 15184,
    "gzipped": 5302
  },
  "dist/umd/popper.min.js": {
    "bundled": 38825,
    "minified": 13144,
    "gzipped": 4620
  },
  "dist/umd/popper-lite.js": {
    "bundled": 29451,
    "minified": 10322,
    "gzipped": 3680
  },
  "dist/umd/popper-lite.min.js": {
    "bundled": 25531,
    "minified": 8395,
    "gzipped": 3036
  },
  "dist/umd/popper-base.js": {
    "bundled": 18973,
    "minified": 6579,
    "gzipped": 2567
  },
  "dist/umd/popper-base.min.js": {
    "bundled": 15053,
    "minified": 4652,
    "gzipped": 1908
  }
}
